<?xml version="1.0" encoding="UTF-8"?>
<!--<!DOCTYPE bibliography PUBLIC "-//OASIS//DTD DocBook XML V4.1.2//EN"
                         "http://www.docbook.org/xml/4.3/docbookx.dtd">-->
<bibliography>
    <bibliodiv>
        <title>Books</title>
        <biblioentry id="gordongraham">
            <authorgroup>
                <author>
                    <firstname>Gordon</firstname>
                    <surname>Graham</surname>
                </author>
            </authorgroup>
            <copyright>
                <year>1987</year>
                <holder>Inventory Management Press</holder>
            </copyright>
            <isbn>0 31701 548 6</isbn>
            <publisher>
                <publishername>Inventory Management Press</publishername>
            </publisher>
            <title>Distribution Inventory Management for the 1990s</title>
        </biblioentry>
        <biblioentry id="colindlewis">
            <authorgroup>
                <author>
                    <firstname>Colin</firstname>
                    <surname>Lewis</surname>
                </author>
            </authorgroup>
            <copyright>
                <year>1997</year>
                <holder>Woodhead Publishing Ltd</holder>
            </copyright>
            <isbn>1 85573 241 6</isbn>
            <publisher>
                <publishername>Woodhead Publishing Ltd</publishername>
            </publisher>
            <title>Demand Forecasting and Inventory Control</title>
            <subtitle>A Computer Aided Learning Approach</subtitle>
        </biblioentry>
        <biblioentry id="edwardfrazelle02">
            <authorgroup>
                <author>
                    <honorific>Dr</honorific>
                    <firstname>Edward</firstname>
                    <surname>Frazelle</surname>
                </author>
            </authorgroup>
            <copyright>
                <year>2002</year>
                <holder>The McGraw-Hill Companies Ltd</holder>
            </copyright>
            <isbn>0 07 137599 6</isbn>
            <publisher>
                <publishername>McGraw-Hill. A division of The McGraw-Hill Companies Ltd</publishername>
            </publisher>
            <title>supply chain Strategy</title>
            <subtitle>The Logistics of supply chain Management</subtitle>
        </biblioentry>
        <biblioentry id="tonywild97">
            <authorgroup>
                <author>
                    <firstname>Tony</firstname>
                    <surname>Wild</surname>
                </author>
            </authorgroup>
            <copyright>
                <year>1997</year>
                <holder>Woodhead Publishing Ltd</holder>
            </copyright>
            <isbn>0 471 25341 3</isbn>
            <publisher>
                <publishername>John Wiley &amp; Sons, Inc</publishername>
            </publisher>
            <title>Best Practice in Inventory Control</title>
        </biblioentry>
        <biblioentry id="michaelhugos03">
            <authorgroup>
                <author>
                    <firstname>Michael</firstname>
                    <surname>Hugos</surname>
                </author>
            </authorgroup>
            <copyright>
                <year>2003</year>
                <holder>John Wiley &amp; Sons, Inc</holder>
            </copyright>
            <isbn>0 471 23517 2</isbn>
            <publisher>
                <publishername>John Wiley &amp; Sons, Inc</publishername>
            </publisher>
            <title>Essentials of supply chain Management</title>
        </biblioentry>
        <biblioentry id="seanwheller03">
            <authorgroup>
                <author>
                    <firstname>Sean</firstname>
                    <surname>Wheller</surname>
                </author>
            </authorgroup>
            <copyright>
                <year>2003</year>
                <holder>SYSPRO (PTY) Ltd. / SYSPRO Press</holder>
            </copyright>
            <isbn>no isbn</isbn>
            <publisher>
                <publishername>SYSPRO (PTY) Ltd. / SYSPRO Press</publishername>
            </publisher>
            <title>SYSPRO e.net solutions</title>
            <subtitle>The Definitive Guide</subtitle>
        </biblioentry>
        <biblioentry id="goldratt92">
            <authorgroup>
                <author>
                    <firstname>Eliyahu</firstname>
                    <surname>Goldratt</surname>
                </author>
                <author>
                    <firstname>Jeff</firstname>
                    <surname>Cox</surname>
                </author>
            </authorgroup>
            <copyright>
                <year>1992</year>
                <holder>North River Press</holder>
            </copyright>
            <isbn>0 884 27061 0</isbn>
            <publisher>
                <publishername>North River Press</publishername>
            </publisher>
            <title>The Goal</title>
            <subtitle>A Process of Ongoing Improvement</subtitle>
        </biblioentry>
        <biblioentry id="kennethmcgee04">
            <authorgroup>
                <author>
                    <firstname>Kenneth</firstname>
                    <surname>Mc Gee</surname>
                </author>
            </authorgroup>
            <copyright>
                <year>2004</year>
                <holder>Gartner, Inc</holder>
            </copyright>
            <isbn>1 59139 299 3</isbn>
            <publisher>
                <publishername>Harvard School Business Press</publishername>
            </publisher>
            <title>Heads Up</title>
            <subtitle>How to Anticipate Business Surprises and Seize Opportunities First</subtitle>
        </biblioentry>
        <biblioentry id="tomasnagle95">
            <authorgroup>
                <author>
                    <firstname>Thomas</firstname>
                    <surname>Nagle</surname>
                </author>
                <author>
                    <firstname>Reed</firstname>
                    <surname>Holden</surname>
                </author>
            </authorgroup>
            <copyright>
                <year>1995,</year>
                <year>1987</year>
                <holder>Prentice-Hall, Inc</holder>
            </copyright>
            <isbn>0 13 669376 8</isbn>
            <publisher>
                <publishername>Prentice-Hall, Inc</publishername>
            </publisher>
            <title>The Strategy and Tactics of Pricing</title>
            <subtitle>A Guide to Profitable Decision Making</subtitle>
        </biblioentry>
        <biblioentry id="tompeters03">
            <authorgroup>
                <author>
                    <firstname>Tom</firstname>
                    <surname>Peters</surname>
                </author>
            </authorgroup>
            <copyright>
                <year>2003</year>
                <holder>Dorling Kindersley Limited</holder>
            </copyright>
            <copyright>
                <year>2003</year>
                <holder>Text: Tom Peters</holder>
            </copyright>
            <isbn>1 4053 0049 3</isbn>
            <publisher>
                <publishername>Dorling Kindersley Limited</publishername>
            </publisher>
            <title>Re-imagine!</title>
            <subtitle>Business Excellence in a Disruptive Age</subtitle>
        </biblioentry>
    </bibliodiv>
    <bibliodiv>
        <title>Papers</title>
        <biblioentry id="jonschreibfeder1">
            <authorgroup>
                <author>
                    <firstname>Jon</firstname>
                    <surname>Schreibfeder</surname>
                </author>
            </authorgroup>
            <copyright>
                <year>2003</year>
                <holder>Microsoft Corporation</holder>
            </copyright>
            <publisher>
                <publishername>Microsoft Business Solutions</publishername>
            </publisher>
            <title>Effective Inventory Analysis</title>
        </biblioentry>
        <biblioentry id="jonschreibfeder2">
            <authorgroup>
                <author>
                    <firstname>Jon</firstname>
                    <surname>Schreibfeder</surname>
                </author>
            </authorgroup>
            <copyright>
                <year>2003</year>
                <holder>Microsoft Corporation</holder>
            </copyright>
            <publisher>
                <publishername>Microsoft Business Solutions</publishername>
            </publisher>
            <title>Effective Replenishment Parameters</title>
        </biblioentry>
        <biblioentry id="jonschreibfeder3">
            <authorgroup>
                <author>
                    <firstname>Jon</firstname>
                    <surname>Schreibfeder</surname>
                </author>
            </authorgroup>
            <copyright>
                <year>2003</year>
                <holder>Microsoft Corporation</holder>
            </copyright>
            <publisher>
                <publishername>Microsoft Business Solutions</publishername>
            </publisher>
            <title>Maintaining Stock in Branch Locations</title>
        </biblioentry>
        <biblioentry id="jonschreibfeder4">
            <authorgroup>
                <author>
                    <firstname>Jon</firstname>
                    <surname>Schreibfeder</surname>
                </author>
            </authorgroup>
            <copyright>
                <year>2003</year>
                <holder>Microsoft Corporation</holder>
            </copyright>
            <publisher>
                <publishername>Microsoft Business Solutions</publishername>
            </publisher>
            <title>Improving the Accuracy of Your Forecasts</title>
        </biblioentry>
        <biblioentry id="jonschreibfeder5">
            <authorgroup>
                <author>
                    <firstname>Jon</firstname>
                    <surname>Schreibfeder</surname>
                </author>
            </authorgroup>
            <copyright>
                <year>2003</year>
                <holder>Microsoft Corporation</holder>
            </copyright>
            <publisher>
                <publishername>Microsoft Business Solutions</publishername>
            </publisher>
            <title>Keeping Stock Balances Accurate</title>
        </biblioentry>
        <biblioentry id="jonschreibfeder6">
            <authorgroup>
                <author>
                    <firstname>Jon</firstname>
                    <surname>Schreibfeder</surname>
                </author>
            </authorgroup>
            <copyright>
                <year>2003</year>
                <holder>Microsoft Corporation</holder>
            </copyright>
            <publisher>
                <publishername>Microsoft Business Solutions</publishername>
            </publisher>
            <title>The First Steps to Achieving Effective Inventory Control</title>
        </biblioentry>
        <biblioentry id="justenough03">
            <copyright>
                <year>2003</year>
                <holder>JustEnough Software Corporation</holder>
            </copyright>
            <publisher>
                <publishername>JustEnough Software Corporation</publishername>
            </publisher>
            <title>Inventory Planning &amp; Optimization: Demand Management</title>
        </biblioentry>
        <biblioentry id="bestsoftware02">
            <copyright>
                <year>2002</year>
                <holder>Best Software, Inc</holder>
            </copyright>
            <publisher>
                <publishername>Best Software, Inc</publishername>
            </publisher>
            <title>Achieving Effective inventory Management</title>
        </biblioentry>
        <biblioentry id="techclarity03">
            <authorgroup>
                <author>
                    <firstname>Jim</firstname>
                    <surname>Brown</surname>
                </author>
            </authorgroup>
            <copyright>
                <year>2003</year>
                <holder>Tech-Clarity Associates</holder>
            </copyright>
            <publisher>
                <publishername>Tech-Clarity Associates</publishername>
            </publisher>
            <title>Optimizing Capacity Deployment and Reducing Capital Investment</title>
            <subtitle>Going Beyond Basic supply chain and Manufacturing in the Process Industries</subtitle>
        </biblioentry>
        <biblioentry id="scormodel">
            <copyright>
                <year>2004</year>
                <holder>The supply chain Council</holder>
            </copyright>
            <publisher>
                <publishername>The supply chain Council</publishername>
            </publisher>
            <title>supply chain Operations Reference-model</title>
        </biblioentry>
        <biblioentry id="cpfrmodel">
            <copyright>
                <year>2004</year>
                <holder>Voluntary Interindustry Commerce Standards</holder>
            </copyright>
            <publisher>
                <publishername>Voluntary Interindustry Commerce Standards</publishername>
            </publisher>
            <title>Collaborative Planning, Forecasting, and Replenishment</title>
            <subtitle>An Overview</subtitle>
        </biblioentry>
    </bibliodiv>
</bibliography>
